acs_student_mail_harvester.py
acs_student_mail_harvester-1.0.1.dist-info/DESCRIPTION.rst
acs_student_mail_harvester-1.0.1.dist-info/METADATA
acs_student_mail_harvester-1.0.1.dist-info/RECORD
acs_student_mail_harvester-1.0.1.dist-info/WHEEL
acs_student_mail_harvester-1.0.1.dist-info/entry_points.txt
acs_student_mail_harvester-1.0.1.dist-info/metadata.json
acs_student_mail_harvester-1.0.1.dist-info/top_level.txt
