Metadata-Version: 2.0
Name: acs-student-mail-harvester
Version: 1.0.1
Summary: Console app and Python API for harvesting email addresses of our ACS students
Home-page: https://github.com/petarmaric/acs_student_mail_harvester
Author: Petar Maric
Author-email: petarmaric@uns.ac.rs
License: BSD
Platform: any
Classifier: Development Status :: 5 - Production/Stable
Classifier: Environment :: Console
Classifier: Intended Audience :: Developers
Classifier: Intended Audience :: Education
Classifier: License :: OSI Approved :: BSD License
Classifier: Operating System :: OS Independent
Classifier: Programming Language :: Python :: 2.7
Classifier: Topic :: Education
Classifier: Topic :: Utilities
Requires-Dist: configobj (<6.0,>=5.0)
